banyan/__init__.py
banyan/clusters.py
banyan/config.py
banyan/constants.py
banyan/id.py
banyan/imports.py
banyan/queues.py
banyan/session.py
banyan/sessions.py
banyan/utils.py
LICENSE
banyan_python-0.2.0.dist-info/LICENSE
banyan_python-0.2.0.dist-info/WHEEL
banyan_python-0.2.0.dist-info/METADATA
banyan_python-0.2.0.dist-info/RECORD
